IntegrationTestRig/IntegrationTestRig.py
IntegrationTestRig/__init__.py
IntegrationTestRig-0.0.14.dist-info/METADATA
IntegrationTestRig-0.0.14.dist-info/WHEEL
IntegrationTestRig-0.0.14.dist-info/top_level.txt
IntegrationTestRig-0.0.14.dist-info/RECORD
