Metadata-Version: 2.1
Name: IntegrationTestRig
Version: 0.0.14
Classifier: Programming Language :: Python :: 3
Classifier: License :: OSI Approved :: MIT License
Classifier: Operating System :: OS Independent
Requires-Python: >=3.6
Requires-Dist: requests
